CHANGELOG.md
starlite_jwt/__init__.py
starlite_jwt/jwt_auth.py
starlite_jwt/middleware.py
starlite_jwt/py.typed
starlite_jwt/token.py
starlite_jwt-1.5.0.dist-info/LICENSE
starlite_jwt-1.5.0.dist-info/WHEEL
starlite_jwt-1.5.0.dist-info/METADATA
starlite_jwt-1.5.0.dist-info/RECORD
