Metadata-Version: 2.1
Name: starlite-jwt
Version: 1.5.0
Summary: A JWT auth toolkit for Starlite
Home-page: https://github.com/starlite-api/jwt-auth
License: MIT
Keywords: starlite,jwt,jwt-token,jwt-auth,jwt-authentication,auth,authentication,middleware,token,apitoken
Author: Na'aman Hirschfeld
Author-email: nhirschfeld@gmail.com
Maintainer: Na'aman Hirschfeld
Maintainer-email: nhirschfeld@gmail.com
Requires-Python: >=3.8,<4.0
Classifier: Development Status :: 5 - Production/Stable
Classifier: Environment :: Web Environment
Classifier: License :: OSI Approved :: MIT License
Classifier: Natural Language :: English
Classifier: Operating System :: OS Independent
Classifier: Programming Language :: Python
Classifier: Programming Language :: Python :: 3
Classifier: Programming Language :: Python :: 3.8
Classifier: Programming Language :: Python :: 3.9
Classifier: Programming Language :: Python :: 3.10
Classifier: Programming Language :: Python :: 3.11
Classifier: Programming Language :: Python :: 3.10
Classifier: Programming Language :: Python :: 3.11
Classifier: Programming Language :: Python :: 3.7
Classifier: Programming Language :: Python :: 3.8
Classifier: Programming Language :: Python :: 3.9
Classifier: Topic :: Internet :: WWW/HTTP
Classifier: Topic :: Software Development
Classifier: Topic :: Software Development :: Libraries
Classifier: Typing :: Typed
Requires-Dist: cryptography
Requires-Dist: python-jose
Requires-Dist: starlite (>=1.24.0)
Project-URL: Documentation, https://github.com/starlite-api/jwt-auth
Project-URL: Repository, https://github.com/starlite-api/jwt-auth
